metafield/__init__.py
metafield/__main__.py
metafield/app.py
metafield/git_utils.py
metafield/llm.py
metafield/nb_depends.py
metafield/nb_utils.py
metafield-0.2.6.dist-info/METADATA
metafield-0.2.6.dist-info/WHEEL
metafield-0.2.6.dist-info/entry_points.txt
metafield-0.2.6.dist-info/top_level.txt
metafield-0.2.6.dist-info/RECORD
